{
    "key": "group_634a3490c5e3f",
    "title": "Featured Listings Block",
    "fields": [
        {
            "key": "field_634a435ffdede",
            "label": "Label",
            "name": "featured_listings_label",
            "type": "text",
            "instructions": "",
            "required": 0,
            "conditional_logic": 0,
            "wrapper": {
                "width": "50",
                "class": "",
                "id": ""
            },
            "default_value": "",
            "placeholder": "",
            "prepend": "",
            "append": "",
            "maxlength": ""
        },
        {
            "key": "field_6350063a1bc85",
            "label": "Property Type",
            "name": "featured_listings_property_type",
            "type": "taxonomy",
            "instructions": "",
            "required": 0,
            "conditional_logic": [
                [
                    {
                        "field": "field_634a34a39b5dc",
                        "operator": "!=",
                        "value": "manual"
                    }
                ]
            ],
            "wrapper": {
                "width": "50",
                "class": "",
                "id": ""
            },
            "taxonomy": "property-types",
            "field_type": "select",
            "allow_null": 1,
            "add_term": 0,
            "save_terms": 0,
            "load_terms": 0,
            "return_format": "id",
            "multiple": 0
        },
        {
            "key": "field_63500748005e9",
            "label": "Show Learn More Button?",
            "name": "featured_listings_learn_more",
            "type": "true_false",
            "instructions": "",
            "required": 0,
            "conditional_logic": 0,
            "wrapper": {
                "width": "50",
                "class": "",
                "id": ""
            },
            "message": "Allow people to learn more about these properties?",
            "default_value": 1,
            "ui": 1,
            "ui_on_text": "",
            "ui_off_text": ""
        },
        {
            "key": "field_6350ccdc64f34",
            "label": "Show Prices?",
            "name": "featured_listings_show_price",
            "type": "true_false",
            "instructions": "",
            "required": 0,
            "conditional_logic": 0,
            "wrapper": {
                "width": "50",
                "class": "",
                "id": ""
            },
            "message": "Display prices in the information card?",
            "default_value": 0,
            "ui": 1,
            "ui_on_text": "",
            "ui_off_text": ""
        },
        {
            "key": "field_6357659a19b4e",
            "label": "Show Details?",
            "name": "featured_listings_show_details",
            "type": "true_false",
            "instructions": "",
            "required": 0,
            "conditional_logic": 0,
            "wrapper": {
                "width": "50",
                "class": "",
                "id": ""
            },
            "message": "Display property details on this block?",
            "default_value": 1,
            "ui": 1,
            "ui_on_text": "",
            "ui_off_text": ""
        },
        {
            "key": "field_634a34a39b5dc",
            "label": "Order",
            "name": "featured_listings_order",
            "type": "radio",
            "instructions": "",
            "required": 0,
            "conditional_logic": 0,
            "wrapper": {
                "width": "50",
                "class": "",
                "id": ""
            },
            "choices": {
                "price": "Price (High to Low)",
                "recent": "Recent",
                "manual": "Manual"
            },
            "allow_null": 0,
            "other_choice": 0,
            "default_value": "",
            "layout": "vertical",
            "return_format": "value",
            "save_other_choice": 0
        },
        {
            "key": "field_634a34cd9b5dd",
            "label": "Manual Order",
            "name": "featured_listings_manual",
            "type": "post_object",
            "instructions": "",
            "required": 1,
            "conditional_logic": [
                [
                    {
                        "field": "field_634a34a39b5dc",
                        "operator": "==",
                        "value": "manual"
                    }
                ]
            ],
            "wrapper": {
                "width": "50",
                "class": "",
                "id": ""
            },
            "post_type": [
                "properties"
            ],
            "taxonomy": "",
            "allow_null": 0,
            "multiple": 1,
            "return_format": "id",
            "ui": 1
        }
    ],
    "location": [
        [
            {
                "param": "block",
                "operator": "==",
                "value": "acf\/custom-blocks-featured-listings"
            }
        ]
    ],
    "menu_order": 0,
    "position": "normal",
    "style": "default",
    "label_placement": "top",
    "instruction_placement": "label",
    "hide_on_screen": "",
    "active": true,
    "description": "",
    "show_in_rest": 0,
    "modified": 1666672082
}